twilog_web_archiver/__init__.py
twilog_web_archiver/main.py
twilog_web_archiver-1.0.1.dist-info/entry_points.txt
twilog_web_archiver-1.0.1.dist-info/LICENSE
twilog_web_archiver-1.0.1.dist-info/WHEEL
twilog_web_archiver-1.0.1.dist-info/METADATA
twilog_web_archiver-1.0.1.dist-info/RECORD
