Metadata-Version: 2.1
Name: twilog-web-archiver
Version: 1.0.1
Summary: Archive twilog website month list pages into Internet Archive Wayback Machine
Home-page: https://github.com/shuuji3/twilog-web-archiver
License: GPL-3.0-or-later
Keywords: twilog,twitter,archive,Wayback Machine,Internet Archive
Author: TAKAHASHI Shuuji
Author-email: shuuji3@gmail.com
Requires-Python: >=3.9,<4.0
Classifier: License :: OSI Approved :: GNU General Public License v3 or later (GPLv3+)
Classifier: Programming Language :: Python :: 3
Classifier: Programming Language :: Python :: 3.9
Requires-Dist: bs4 (>=0.0.1,<0.0.2)
Requires-Dist: click (>=8.0,<9.0)
Requires-Dist: lxml (>=4.3,<5.0)
Requires-Dist: pluggy (>=0.13.1,<0.14.0)
Requires-Dist: requests (>=2.21,<3.0)
Requires-Dist: waybackpy (>=3.0.6,<4.0.0)
Project-URL: Repository, https://github.com/shuuji3/twilog-web-archiver
